iiitb_sfifo.v

`timescale 1 ns/ 1 ps
module iiitb_sfifo(
	input        CLK,
	input        RSTn,
	input        write,
	input        read,
	input  [7:0] iData,
	
	output [7:0] oData,
	output       full,
	output       empty
);

reg [4:0] wp;          //write point should add 1 bit(N+1) 
reg [4:0] rp;          //read point
reg [7:0] RAM [15:0];  //deep16,8 bit RAM
reg [7:0] oData_reg;   //regsiter of oData

always @ ( posedge CLK or negedge RSTn )
begin                  //write to RAM
	if (!RSTn)
	begin
		wp <= 5'b0;
	end
	else if ( write )
	begin
		RAM[wp[3:0]] <= iData;
		wp <= wp + 1'b1;
	end
end

always @ ( posedge CLK or negedge RSTn )
begin                  // read from RAM
	if (!RSTn)
	begin
		rp <= 5'b0;
		oData_reg <= 8'b0;
	end
	else if ( read  )
	begin
		oData_reg <= RAM[rp[3:0]];
		rp <= rp + 1'b1;
	end
end


assign full = ( wp[4] ^ rp[4] & wp[3:0] == rp[3:0] );
assign empty = ( wp == rp );
assign oData = oData_reg;


endmodule

iiitb_sfifo_tb.v

`timescale 1 ns/ 1 ps
module iiitb_sfifo_tb();
	reg CLK;
	reg RSTn;
	reg write;
	reg read;
	reg [7:0] iData;
	
	wire [7:0] oData;
	wire full;
	wire empty;

initial
begin
	read=0;
	write=0;
end
initial
begin
	CLK <= 1'b0;
	forever #100 CLK <= ~CLK;
end


initial 
begin
	RSTn = 0;
	iData = 0;
	#10 RSTn = 1;
end
	
always @ (posedge CLK or negedge RSTn)
begin
	iData <= iData + 1'b1;
				  
end

always @ (posedge CLK or negedge RSTn)
begin
	if (!RSTn)
		write = 0;
	else if (!full)
	begin
		write = 1;
	end
	else 
		write = 0;
end

always @ (posedge CLK or negedge RSTn)
begin
	if (!RSTn)
		read = 0;
	else if (!empty)
		read = 1;
	else 
		read = 0;
end


iiitb_sfifo fifo (.CLK(CLK),
				  .RSTn(RSTn),
				  .write(write),
				  .read(read),
				  .iData(iData),
				  .full(full),
				  .empty(empty),
				  .oData(oData));

  initial begin
    $dumpfile("dump.vcd");
    $dumpvars;
  end
  initial
  #20000 $finish;
             
endmodule

dump.vcd
$date
	Mon Sep  5 23:37:05 2022
$end
$version
	Icarus Verilog
$end
$timescale
	1ps
$end
$scope module iiitb_sfifo_tb $end
$var wire 8 ! oData [7:0] $end
$var wire 1 " full $end
$var wire 1 # empty $end
$var reg 1 $ CLK $end
$var reg 1 % RSTn $end
$var reg 8 & iData [7:0] $end
$var reg 1 ' read $end
$var reg 1 ( write $end
$scope module fifo $end
$var wire 1 $ CLK $end
$var wire 1 % RSTn $end
$var wire 1 " full $end
$var wire 8 ) iData [7:0] $end
$var wire 8 * oData [7:0] $end
$var wire 1 ' read $end
$var wire 1 ( write $end
$var wire 1 # empty $end
$var reg 8 + oData_reg [7:0] $end
$var reg 5 , rp [4:0] $end
$var reg 5 - wp [4:0] $end
$upscope $end
$upscope $end
$enddefinitions $end
#0
$dumpvars
b0 -
b0 ,
b0 +
b0 *
b0 )
0(
0'
b0 &
0%
0$
1#
0"
b0 !
$end
#10000
1%
#100000
b1 &
b1 )
1(
1$
#200000
0$
#300000
0#
b1 -
b10 &
b10 )
1$
#400000
0$
#500000
b11 &
b11 )
b10 -
1'
1$
#600000
0$
#700000
b11 -
b1 ,
b1 !
b1 *
b1 +
b100 &
b100 )
1$
#800000
0$
#900000
b101 &
b101 )
b10 ,
b10 !
b10 *
b10 +
b100 -
1$
#1000000
0$
#1100000
b101 -
b11 ,
b11 !
b11 *
b11 +
b110 &
b110 )
1$
#1200000
0$
#1300000
b111 &
b111 )
b100 ,
b100 !
b100 *
b100 +
b110 -
1$
#1400000
0$
#1500000
b111 -
b101 ,
b101 !
b101 *
b101 +
b1000 &
b1000 )
1$
#1600000
0$
#1700000
b1001 &
b1001 )
b110 ,
b110 !
b110 *
b110 +
b1000 -
1$
#1800000
0$
#1900000
b1001 -
b111 ,
b111 !
b111 *
b111 +
b1010 &
b1010 )
1$
#2000000
0$
#2100000
b1011 &
b1011 )
b1000 ,
b1000 !
b1000 *
b1000 +
b1010 -
1$
#2200000
0$
#2300000
b1011 -
b1001 ,
b1001 !
b1001 *
b1001 +
b1100 &
b1100 )
1$
#2400000
0$
#2500000
b1101 &
b1101 )
b1010 ,
b1010 !
b1010 *
b1010 +
b1100 -
1$
#2600000
0$
#2700000
b1101 -
b1011 ,
b1011 !
b1011 *
b1011 +
b1110 &
b1110 )
1$
#2800000
0$
#2900000
b1111 &
b1111 )
b1100 ,
b1100 !
b1100 *
b1100 +
b1110 -
1$
#3000000
0$
#3100000
b1111 -
b1101 ,
b1101 !
b1101 *
b1101 +
b10000 &
b10000 )
1$
#3200000
0$
#3300000
1"
b10001 &
b10001 )
b1110 ,
b1110 !
b1110 *
b1110 +
b10000 -
1$
#3400000
0$
#3500000
b1111 ,
b1111 !
b1111 *
b1111 +
b10010 &
b10010 )
0(
1$
#3600000
0$
#3700000
0"
b10011 &
b10011 )
1#
b10000 ,
b10000 !
b10000 *
b10000 +
1$
#3800000
0$
#3900000
1"
0#
b10001 -
b10100 &
b10100 )
0'
1(
1$
#4000000
0$
#4100000
b10101 &
b10101 )
b10010 -
0(
1'
1$
#4200000
0$
#4300000
b10001 ,
b10011 !
b10011 *
b10011 +
b10110 &
b10110 )
1$
#4400000
0$
#4500000
0"
b10111 &
b10111 )
1#
b10010 ,
b10100 !
b10100 *
b10100 +
1$
#4600000
0$
#4700000
1"
0#
b10011 -
b11000 &
b11000 )
0'
1(
1$
#4800000
0$
#4900000
b11001 &
b11001 )
b10100 -
0(
1'
1$
#5000000
0$
#5100000
b10011 ,
b10111 !
b10111 *
b10111 +
b11010 &
b11010 )
1$
#5200000
0$
#5300000
0"
b11011 &
b11011 )
1#
b10100 ,
b11000 !
b11000 *
b11000 +
1$
#5400000
0$
#5500000
1"
0#
b10101 -
b11100 &
b11100 )
0'
1(
1$
#5600000
0$
#5700000
b11101 &
b11101 )
b10110 -
0(
1'
1$
#5800000
0$
#5900000
b10101 ,
b11011 !
b11011 *
b11011 +
b11110 &
b11110 )
1$
#6000000
0$
#6100000
0"
b11111 &
b11111 )
1#
b10110 ,
b11100 !
b11100 *
b11100 +
1$
#6200000
0$
#6300000
1"
0#
b10111 -
b100000 &
b100000 )
0'
1(
1$
#6400000
0$
#6500000
b100001 &
b100001 )
b11000 -
0(
1'
1$
#6600000
0$
#6700000
b10111 ,
b11111 !
b11111 *
b11111 +
b100010 &
b100010 )
1$
#6800000
0$
#6900000
0"
b100011 &
b100011 )
1#
b11000 ,
b100000 !
b100000 *
b100000 +
1$
#7000000
0$
#7100000
1"
0#
b11001 -
b100100 &
b100100 )
0'
1(
1$
#7200000
0$
#7300000
b100101 &
b100101 )
b11010 -
0(
1'
1$
#7400000
0$
#7500000
b11001 ,
b100011 !
b100011 *
b100011 +
b100110 &
b100110 )
1$
#7600000
0$
#7700000
0"
b100111 &
b100111 )
1#
b11010 ,
b100100 !
b100100 *
b100100 +
1$
#7800000
0$
#7900000
1"
0#
b11011 -
b101000 &
b101000 )
0'
1(
1$
#8000000
0$
#8100000
b101001 &
b101001 )
b11100 -
0(
1'
1$
#8200000
0$
#8300000
b11011 ,
b100111 !
b100111 *
b100111 +
b101010 &
b101010 )
1$
#8400000
0$
#8500000
0"
b101011 &
b101011 )
1#
b11100 ,
b101000 !
b101000 *
b101000 +
1$
#8600000
0$
#8700000
1"
0#
b11101 -
b101100 &
b101100 )
0'
1(
1$
#8800000
0$
#8900000
b101101 &
b101101 )
b11110 -
0(
1'
1$
#9000000
0$
#9100000
b11101 ,
b101011 !
b101011 *
b101011 +
b101110 &
b101110 )
1$
#9200000
0$
#9300000
0"
b101111 &
b101111 )
1#
b11110 ,
b101100 !
b101100 *
b101100 +
1$
#9400000
0$
#9500000
1"
0#
b11111 -
b110000 &
b110000 )
0'
1(
1$
#9600000
0$
#9700000
0"
b110001 &
b110001 )
b0 -
0(
1'
1$
#9800000
0$
#9900000
b1 -
b11111 ,
b101111 !
b101111 *
b101111 +
b110010 &
b110010 )
1(
1$
#10000000
0$
#10100000
b110011 &
b110011 )
b0 ,
b110000 !
b110000 *
b110000 +
b10 -
1$
#10200000
0$
#10300000
b11 -
b1 ,
b110001 !
b110001 *
b110001 +
b110100 &
b110100 )
1$
#10400000
0$
#10500000
b110101 &
b110101 )
b10 ,
b110010 !
b110010 *
b110010 +
b100 -
1$
#10600000
0$
#10700000
b101 -
b11 ,
b110011 !
b110011 *
b110011 +
b110110 &
b110110 )
1$
#10800000
0$
#10900000
b110111 &
b110111 )
b100 ,
b110100 !
b110100 *
b110100 +
b110 -
1$
#11000000
0$
#11100000
b111 -
b101 ,
b110101 !
b110101 *
b110101 +
b111000 &
b111000 )
1$
#11200000
0$
#11300000
b111001 &
b111001 )
b110 ,
b110110 !
b110110 *
b110110 +
b1000 -
1$
#11400000
0$
#11500000
b1001 -
b111 ,
b110111 !
b110111 *
b110111 +
b111010 &
b111010 )
1$
#11600000
0$
#11700000
b111011 &
b111011 )
b1000 ,
b111000 !
b111000 *
b111000 +
b1010 -
1$
#11800000
0$
#11900000
b1011 -
b1001 ,
b111001 !
b111001 *
b111001 +
b111100 &
b111100 )
1$
#12000000
0$
#12100000
b111101 &
b111101 )
b1010 ,
b111010 !
b111010 *
b111010 +
b1100 -
1$
#12200000
0$
#12300000
b1101 -
b1011 ,
b111011 !
b111011 *
b111011 +
b111110 &
b111110 )
1$
#12400000
0$
#12500000
b111111 &
b111111 )
b1100 ,
b111100 !
b111100 *
b111100 +
b1110 -
1$
#12600000
0$
#12700000
b1111 -
b1101 ,
b111101 !
b111101 *
b111101 +
b1000000 &
b1000000 )
1$
#12800000
0$
#12900000
1"
b1000001 &
b1000001 )
b1110 ,
b111110 !
b111110 *
b111110 +
b10000 -
1$
#13000000
0$
#13100000
b1111 ,
b111111 !
b111111 *
b111111 +
b1000010 &
b1000010 )
0(
1$
#13200000
0$
#13300000
0"
b1000011 &
b1000011 )
1#
b10000 ,
b1000000 !
b1000000 *
b1000000 +
1$
#13400000
0$
#13500000
1"
0#
b10001 -
b1000100 &
b1000100 )
0'
1(
1$
#13600000
0$
#13700000
b1000101 &
b1000101 )
b10010 -
0(
1'
1$
#13800000
0$
#13900000
b10001 ,
b1000011 !
b1000011 *
b1000011 +
b1000110 &
b1000110 )
1$
#14000000
0$
#14100000
0"
b1000111 &
b1000111 )
1#
b10010 ,
b1000100 !
b1000100 *
b1000100 +
1$
#14200000
0$
#14300000
1"
0#
b10011 -
b1001000 &
b1001000 )
0'
1(
1$
#14400000
0$
#14500000
b1001001 &
b1001001 )
b10100 -
0(
1'
1$
#14600000
0$
#14700000
b10011 ,
b1000111 !
b1000111 *
b1000111 +
b1001010 &
b1001010 )
1$
#14800000
0$
#14900000
0"
b1001011 &
b1001011 )
1#
b10100 ,
b1001000 !
b1001000 *
b1001000 +
1$
#15000000
0$
#15100000
1"
0#
b10101 -
b1001100 &
b1001100 )
0'
1(
1$
#15200000
0$
#15300000
b1001101 &
b1001101 )
b10110 -
0(
1'
1$
#15400000
0$
#15500000
b10101 ,
b1001011 !
b1001011 *
b1001011 +
b1001110 &
b1001110 )
1$
#15600000
0$
#15700000
0"
b1001111 &
b1001111 )
1#
b10110 ,
b1001100 !
b1001100 *
b1001100 +
1$
#15800000
0$
#15900000
1"
0#
b10111 -
b1010000 &
b1010000 )
0'
1(
1$
#16000000
0$
#16100000
b1010001 &
b1010001 )
b11000 -
0(
1'
1$
#16200000
0$
#16300000
b10111 ,
b1001111 !
b1001111 *
b1001111 +
b1010010 &
b1010010 )
1$
#16400000
0$
#16500000
0"
b1010011 &
b1010011 )
1#
b11000 ,
b1010000 !
b1010000 *
b1010000 +
1$
#16600000
0$
#16700000
1"
0#
b11001 -
b1010100 &
b1010100 )
0'
1(
1$
#16800000
0$
#16900000
b1010101 &
b1010101 )
b11010 -
0(
1'
1$
#17000000
0$
#17100000
b11001 ,
b1010011 !
b1010011 *
b1010011 +
b1010110 &
b1010110 )
1$
#17200000
0$
#17300000
0"
b1010111 &
b1010111 )
1#
b11010 ,
b1010100 !
b1010100 *
b1010100 +
1$
#17400000
0$
#17500000
1"
0#
b11011 -
b1011000 &
b1011000 )
0'
1(
1$
#17600000
0$
#17700000
b1011001 &
b1011001 )
b11100 -
0(
1'
1$
#17800000
0$
#17900000
b11011 ,
b1010111 !
b1010111 *
b1010111 +
b1011010 &
b1011010 )
1$
#18000000
0$
#18100000
0"
b1011011 &
b1011011 )
1#
b11100 ,
b1011000 !
b1011000 *
b1011000 +
1$
#18200000
0$
#18300000
1"
0#
b11101 -
b1011100 &
b1011100 )
0'
1(
1$
#18400000
0$
#18500000
b1011101 &
b1011101 )
b11110 -
0(
1'
1$
#18600000
0$
#18700000
b11101 ,
b1011011 !
b1011011 *
b1011011 +
b1011110 &
b1011110 )
1$
#18800000
0$
#18900000
0"
b1011111 &
b1011111 )
1#
b11110 ,
b1011100 !
b1011100 *
b1011100 +
1$
#19000000
0$
#19100000
1"
0#
b11111 -
b1100000 &
b1100000 )
0'
1(
1$
#19200000
0$
#19300000
0"
b1100001 &
b1100001 )
b0 -
0(
1'
1$
#19400000
0$
#19500000
b1 -
b11111 ,
b1011111 !
b1011111 *
b1011111 +
b1100010 &
b1100010 )
1(
1$
#19600000
0$
#19700000
b1100011 &
b1100011 )
b0 ,
b1100000 !
b1100000 *
b1100000 +
b10 -
1$
#19800000
0$
#19900000
b11 -
b1 ,
b1100001 !
b1100001 *
b1100001 +
b1100100 &
b1100100 )
1$
